{
  "info": {
    "_postman_id": "4e918ac6-d44f-4646-8581-0501d846313a",
    "name": "Final Project Movie",
    "schema": "https://schema.getpostman.com/json/collection/v2.1.0/collection.json",
    "_exporter_id": "53699635",
    "_collection_link": "https://go.postman.co/collection/53699635-4e918ac6-d44f-4646-8581-0501d846313a?source=collection_link"
  },
  "item": [
    {
      "name": "Get movies",
      "protocolProfileBehavior": {
        "disableBodyPruning": true
      },
      "request": {
        "method": "GET",
        "header": [],
        "body": {
          "mode": "raw",
          "raw": "",
          "options": {
            "raw": {
              "language": "json"
            }
          }
        },
        "url": {
          "raw": "{{baseUrl}}/movies",
          "host": [
            "{{baseUrl}}"
          ],
          "path": [
            "movies"
          ]
        }
      },
      "response": []
    },
    {
      "name": "Get movie by ID",
      "protocolProfileBehavior": {
        "disableBodyPruning": true
      },
      "request": {
        "method": "GET",
        "header": [],
        "body": {
          "mode": "raw",
          "raw": "",
          "options": {
            "raw": {
              "language": "json"
            }
          }
        },
        "url": {
          "raw": "{{baseUrl}}/movies/4",
          "host": [
            "{{baseUrl}}"
          ],
          "path": [
            "movies",
            "4"
          ]
        }
      },
      "response": []
    },
    {
      "name": "Get movie with filtering",
      "protocolProfileBehavior": {
        "disableBodyPruning": true
      },
      "request": {
        "method": "GET",
        "header": [],
        "body": {
          "mode": "raw",
          "raw": "",
          "options": {
            "raw": {
              "language": "json"
            }
          }
        },
        "url": {
          "raw": "{{baseUrl}}/movies?genre=Comedy",
          "host": [
            "{{baseUrl}}"
          ],
          "path": [
            "movies"
          ],
          "query": [
            {
              "key": "genre",
              "value": "Comedy"
            }
          ]
        }
      },
      "response": []
    },
    {
      "name": "POST movies",
      "request": {
        "method": "POST",
        "header": [],
        "body": {
          "mode": "raw",
          "raw": "{ \r\n    \"title\": \"Bee Movie\",\r\n    \"release_year\": \"2007\",\r\n    \"genre\": \"Comedy\",\r\n    \"rating\": \"\",\r\n    \"watched\": 1\r\n\r\n}",
          "options": {
            "raw": {
              "language": "json"
            }
          }
        },
        "url": {
          "raw": "{{baseUrl}}/movies",
          "host": [
            "{{baseUrl}}"
          ],
          "path": [
            "movies"
          ]
        }
      },
      "response": []
    },
    {
      "name": "PUT update movies",
      "request": {
        "method": "PUT",
        "header": [],
        "body": {
          "mode": "raw",
          "raw": "{ \r\n    \"title\": \"Bee Movie\",\r\n    \"release_year\": \"2007\",\r\n    \"genre\": \"Comedy\",\r\n    \"rating\": 7,\r\n    \"watched\": true\r\n}",
          "options": {
            "raw": {
              "language": "json"
            }
          }
        },
        "url": {
          "raw": "{{baseUrl}}/movies/4",
          "host": [
            "{{baseUrl}}"
          ],
          "path": [
            "movies",
            "4"
          ]
        }
      },
      "response": []
    },
    {
      "name": "DELETE movie by ID",
      "request": {
        "method": "DELETE",
        "header": [],
        "body": {
          "mode": "raw",
          "raw": "",
          "options": {
            "raw": {
              "language": "json"
            }
          }
        },
        "url": {
          "raw": "{{baseUrl}}/movies/4",
          "host": [
            "{{baseUrl}}"
          ],
          "path": [
            "movies",
            "4"
          ]
        }
      },
      "response": []
    }
  ]
}